tictoc.py
easy_tic_toc-0.0.1.dist-info/LICENSE
easy_tic_toc-0.0.1.dist-info/METADATA
easy_tic_toc-0.0.1.dist-info/WHEEL
easy_tic_toc-0.0.1.dist-info/top_level.txt
easy_tic_toc-0.0.1.dist-info/RECORD
